tree_queries/__init__.py
tree_queries/admin.py
tree_queries/compiler.py
tree_queries/fields.py
tree_queries/forms.py
tree_queries/models.py
tree_queries/query.py
tree_queries/locale/de/LC_MESSAGES/django.mo
tree_queries/locale/de/LC_MESSAGES/django.po
tree_queries/static/tree_queries/tree_admin.css
tree_queries/static/tree_queries/tree_admin.js
tree_queries/templatetags/__init__.py
tree_queries/templatetags/tree_queries.py
django_tree_queries-0.22.0.dist-info/METADATA
django_tree_queries-0.22.0.dist-info/WHEEL
django_tree_queries-0.22.0.dist-info/licenses/LICENSE
django_tree_queries-0.22.0.dist-info/RECORD
