Metadata-Version: 2.4
Name: django-tree-queries
Version: 0.22.0
Summary: Tree queries with explicit opt-in, without configurability
Project-URL: Homepage, https://github.com/matthiask/django-tree-queries/
Author-email: Matthias Kestenholz <mk@feinheit.ch>
License: BSD-3-Clause
License-File: LICENSE
Classifier: Environment :: Web Environment
Classifier: Framework :: Django
Classifier: Intended Audience :: Developers
Classifier: License :: OSI Approved :: BSD License
Classifier: Operating System :: OS Independent
Classifier: Programming Language :: Python
Classifier: Programming Language :: Python :: 3 :: Only
Classifier: Programming Language :: Python :: 3.8
Classifier: Programming Language :: Python :: 3.9
Classifier: Programming Language :: Python :: 3.10
Classifier: Programming Language :: Python :: 3.11
Classifier: Programming Language :: Python :: 3.12
Classifier: Programming Language :: Python :: 3.13
Classifier: Programming Language :: Python :: 3.14
Classifier: Topic :: Internet :: WWW/HTTP :: Dynamic Content
Classifier: Topic :: Software Development
Requires-Python: >=3.8
Provides-Extra: admin
Requires-Dist: django-js-asset; extra == 'admin'
Provides-Extra: tests
Requires-Dist: coverage; extra == 'tests'
Requires-Dist: django-js-asset; extra == 'tests'
Requires-Dist: pytest; extra == 'tests'
Requires-Dist: pytest-cov; extra == 'tests'
Requires-Dist: pytest-django; extra == 'tests'
